ssu_tf_keras/__init__.py
ssu_tf_keras/layers.py
ssu_tk-0.0.0.1.1.dist-info/METADATA
ssu_tk-0.0.0.1.1.dist-info/RECORD
ssu_tk-0.0.0.1.1.dist-info/WHEEL
ssu_tk-0.0.0.1.1.dist-info/top_level.txt
